electrical_formula/__init__.py
electrical_formula/ohmlaw.py
electrical_formula-0.1.dist-info/METADATA
electrical_formula-0.1.dist-info/WHEEL
electrical_formula-0.1.dist-info/dependency_links.txt
electrical_formula-0.1.dist-info/top_level.txt
electrical_formula-0.1.dist-info/RECORD
