Metadata-Version: 2.1
Name: electrical-formula
Version: 0.1
Summary: The formula of electrical enginering 
Home-page: https://github.com/zizonk/electrical-formula.git
Author: M afif Nur Azizi
Author-email: afifnurazizi@gmail.com
License: MIT
Platform: UNKNOWN
